.gitignore
LICENSE
MANIFEST.in
README.md
pyproject.toml
requirements.txt
setup.py
src/MacrophageAnalysisToolkit.py
src/MAT/BDD.py
src/MAT/BDDPlotter.py
src/MAT/CalibPoints.py
src/MAT/Calibrator.py
src/MAT/RegionSel.py
src/MAT/Runner.py
src/MAT/SelWin.py
src/MAT/__init__.py
src/hundlab_MAT.egg-info/PKG-INFO
src/hundlab_MAT.egg-info/SOURCES.txt
src/hundlab_MAT.egg-info/dependency_links.txt
src/hundlab_MAT.egg-info/requires.txt
src/hundlab_MAT.egg-info/top_level.txt