Metadata-Version: 2.1
Name: hundlab-MAT
Version: 1.0
Summary: Macrophage Analysis Toolkit: A tool to quantify macrophage presence
Home-page: https://github.com/hundlab/MAT
Author: Thomas Hund
Author-email: hund.1@osu.edu
License: MIT
Platform: UNKNOWN
License-File: LICENSE
